CHANGELOG.txt
LICENCE.txt
MANIFEST.in
README.txt
setup.py
hellofrommoshe.egg-info/PKG-INFO
hellofrommoshe.egg-info/SOURCES.txt
hellofrommoshe.egg-info/dependency_links.txt
hellofrommoshe.egg-info/top_level.txt
myhello/__init__.py