Metadata-Version: 2.1
Name: hellofrommoshe
Version: 0.0.1
Summary: print hello
Home-page: UNKNOWN
Author: Moshe Rosenblum
Author-email: mosherosenblum1@gmail.com
License: MIT
Keywords: hello
Platform: UNKNOWN
Classifier: Development Status :: 5 - Production/Stable
Classifier: Intended Audience :: Education
Classifier: Operating System :: Microsoft :: Windows :: Windows 10
Classifier: License :: OSI Approved :: MIT License
Classifier: Programming Language :: Python :: 3
License-File: LICENCE.txt
